virtue/__init__.py
virtue/__main__.py
virtue/_cli.py
virtue/loaders.py
virtue/locators.py
virtue/reporters.py
virtue/runner.py
virtue/tests/__init__.py
virtue/tests/test_cli.py
virtue/tests/test_loaders.py
virtue/tests/test_locators.py
virtue/tests/test_reporters.py
virtue/tests/test_runner.py
virtue/tests/samples/__init__.py
virtue/tests/samples/dynamic_test.py
virtue/tests/samples/failures_and_errors.py
virtue/tests/samples/failures_and_unexpected_passes.py
virtue/tests/samples/mixin.py
virtue/tests/samples/module_for_TestLoaders.py
virtue/tests/samples/module_for_TestObjectLocator.py
virtue/tests/samples/module_with_exception.py
virtue/tests/samples/no_tests.py
virtue/tests/samples/one_expected_failure.py
virtue/tests/samples/one_expected_failure_mispassing.py
virtue/tests/samples/one_successful_test.py
virtue/tests/samples/one_unsuccessful_test.py
virtue/tests/samples/repeated_similar_output.py
virtue/tests/samples/subtests.py
virtue/tests/samples/success_and_warning.py
virtue/tests/samples/two_unsuccessful_tests.py
virtue-2025.2.1.dist-info/METADATA
virtue-2025.2.1.dist-info/WHEEL
virtue-2025.2.1.dist-info/entry_points.txt
virtue-2025.2.1.dist-info/licenses/COPYING
virtue-2025.2.1.dist-info/RECORD
