Metadata-Version: 2.4
Name: virtue
Version: 2025.2.1
Summary: After trial comes virtue. A test runner for good.
Project-URL: Documentation, https://virtue.readthedocs.io/
Project-URL: Homepage, https://github.com/Julian/Virtue
Project-URL: Issues, https://github.com/Julian/Virtue/issues/
Project-URL: Funding, https://github.com/sponsors/Julian
Project-URL: Source, https://github.com/Julian/Virtue
Author-email: Julian Berman <Julian+Virtue@GrayVines.com>
License-Expression: MIT
License-File: COPYING
Keywords: test runner,testing,tests,unittest
Classifier: Development Status :: 5 - Production/Stable
Classifier: Intended Audience :: Developers
Classifier: Operating System :: OS Independent
Classifier: Programming Language :: Python
Classifier: Programming Language :: Python :: 3.9
Classifier: Programming Language :: Python :: 3.10
Classifier: Programming Language :: Python :: 3.11
Classifier: Programming Language :: Python :: 3.12
Classifier: Programming Language :: Python :: 3.13
Classifier: Programming Language :: Python :: Implementation :: CPython
Classifier: Programming Language :: Python :: Implementation :: PyPy
Requires-Python: >=3.9
Requires-Dist: attrs>=22.2.0
Requires-Dist: click
Requires-Dist: colorama
Requires-Dist: pyrsistent
Requires-Dist: twisted>=23.10.0rc1
